README.md
setup.py
fast_image_extract/__init__.py
fast_image_extract/website_one.py
fast_image_extract.egg-info/PKG-INFO
fast_image_extract.egg-info/SOURCES.txt
fast_image_extract.egg-info/dependency_links.txt
fast_image_extract.egg-info/top_level.txt