Metadata-Version: 2.1
Name: fast-image-extract
Version: 0.0.1
Summary: Provide image url, location, name for file to be downloaded
Author: Shannon Smith
License: UNKNOWN
Platform: UNKNOWN
